{
  "formatVersion": 1,
  "database": {
    "version": 2,
    "identityHash": "5688fea65882f2392d38acfc7ec06f8c",
    "entities": [
      {
        "tableName": "PhoneNumRecord",
        "createSql": "CREATE TABLE IF NOT EXISTS `${TABLE_NAME}` (`id` INTEGER PRIMARY KEY AUTOINCREMENT NOT NULL, `prefix` TEXT NOT NULL, `phoneNum` TEXT NOT NULL, `accessDate` INTEGER NOT NULL, `contactName` TEXT NOT NULL, `pin` INTEGER NOT NULL)",
        "fields": [
          {
            "fieldPath": "id",
            "columnName": "id",
            "affinity": "INTEGER",
            "notNull": true
          },
          {
            "fieldPath": "prefix",
            "columnName": "prefix",
            "affinity": "TEXT",
            "notNull": true
          },
          {
            "fieldPath": "phoneNum",
            "columnName": "phoneNum",
            "affinity": "TEXT",
            "notNull": true
          },
          {
            "fieldPath": "accessDate",
            "columnName": "accessDate",
            "affinity": "INTEGER",
            "notNull": true
          },
          {
            "fieldPath": "contactName",
            "columnName": "contactName",
            "affinity": "TEXT",
            "notNull": true
          },
          {
            "fieldPath": "pin",
            "columnName": "pin",
            "affinity": "INTEGER",
            "notNull": true
          }
        ],
        "primaryKey": {
          "columnNames": [
            "id"
          ],
          "autoGenerate": true
        },
        "indices": [
          {
            "name": "index_PhoneNumRecord_prefix_phoneNum",
            "unique": true,
            "columnNames": [
              "prefix",
              "phoneNum"
            ],
            "createSql": "CREATE UNIQUE INDEX `index_PhoneNumRecord_prefix_phoneNum` ON `${TABLE_NAME}` (`prefix`, `phoneNum`)"
          }
        ],
        "foreignKeys": []
      }
    ],
    "views": [],
    "setupQueries": [
      "CREATE TABLE IF NOT EXISTS room_master_table (id INTEGER PRIMARY KEY,identity_hash TEXT)",
      "INSERT OR REPLACE INTO room_master_table (id,identity_hash) VALUES(42, '5688fea65882f2392d38acfc7ec06f8c')"
    ]
  }
}